__init__.py
utilities.py
calculator/calculator.py
crypto/b64.py
crypto/caesar.py
crypto/morse.py
crypto/utils.py
crypto/vigenere.py
date/date.py
shutdown/shutdown.py
timer/timer.py
UnstableUtilities-1.1.1.dist-info/LICENSE
UnstableUtilities-1.1.1.dist-info/METADATA
UnstableUtilities-1.1.1.dist-info/WHEEL
UnstableUtilities-1.1.1.dist-info/top_level.txt
UnstableUtilities-1.1.1.dist-info/RECORD
