Metadata-Version: 2.1
Name: UnstableUtilities
Version: 1.1.1
Summary: A utility tool that sometimes works :D
Author-email: Thomas Chen <jc10883@nyu.edu>, Edison Wang <zw3165@nyu.edu>, Annabella Lee <pl2220@nyu.edu>, An Hai <ah6253@nyu.edu>
License: GNU GENERAL PUBLIC LICENSE
Project-URL: Homepage, https://github.com/software-students-fall2024/3-python-package-this-package
Keywords: unstable,crypto,calculator,shutdown,timer,date
Classifier: License :: OSI Approved :: GNU General Public License (GPL)
Classifier: Programming Language :: Python
Classifier: Programming Language :: Python :: 3
License-File: LICENSE
Provides-Extra: dev
Requires-Dist: pytest; extra == "dev"
